GormZhongwenWendangFix1/README.md
GormZhongwenWendangFix1/__init__.py
GormZhongwenWendangFix1/__main__.py
GormZhongwenWendangFix1/file.epub
GormZhongwenWendangFix1/index.html
GormZhongwenWendangFix1/css/__init__.py
GormZhongwenWendangFix1/css/annotations.css
GormZhongwenWendangFix1/css/main.css
GormZhongwenWendangFix1/css/normalize.css
GormZhongwenWendangFix1/css/popup.css
GormZhongwenWendangFix1/font/__init__.py
GormZhongwenWendangFix1/font/fontello.eot
GormZhongwenWendangFix1/font/fontello.svg
GormZhongwenWendangFix1/font/fontello.ttf
GormZhongwenWendangFix1/font/fontello.woff
GormZhongwenWendangFix1/img/__init__.py
GormZhongwenWendangFix1/img/annotator-glyph-sprite.png
GormZhongwenWendangFix1/img/annotator-icon-sprite.png
GormZhongwenWendangFix1/img/apple-touch-icon.png
GormZhongwenWendangFix1/img/cancelfullscreen.png
GormZhongwenWendangFix1/img/close.png
GormZhongwenWendangFix1/img/fullscreen.png
GormZhongwenWendangFix1/img/loader.gif
GormZhongwenWendangFix1/img/menu-icon.png
GormZhongwenWendangFix1/img/save.png
GormZhongwenWendangFix1/img/saved.png
GormZhongwenWendangFix1/img/settings-s.png
GormZhongwenWendangFix1/img/settings.png
GormZhongwenWendangFix1/img/star.png
GormZhongwenWendangFix1/js/__init__.py
GormZhongwenWendangFix1/js/epub.js
GormZhongwenWendangFix1/js/epub.min.js
GormZhongwenWendangFix1/js/epub.min.map
GormZhongwenWendangFix1/js/hooks.min.js
GormZhongwenWendangFix1/js/hooks.min.map
GormZhongwenWendangFix1/js/reader.js
GormZhongwenWendangFix1/js/reader.js.map
GormZhongwenWendangFix1/js/reader.min.js
GormZhongwenWendangFix1/js/reader.min.map
GormZhongwenWendangFix1/js/hooks/__init__.py
GormZhongwenWendangFix1/js/hooks/extensions/__init__.py
GormZhongwenWendangFix1/js/hooks/extensions/highlight.js
GormZhongwenWendangFix1/js/libs/__init__.py
GormZhongwenWendangFix1/js/libs/jquery.min.js
GormZhongwenWendangFix1/js/libs/localforage.min.js
GormZhongwenWendangFix1/js/libs/screenfull.js
GormZhongwenWendangFix1/js/libs/screenfull.min.js
gorm_zhongwen_wendang_fix1-2025.3.25.1.dist-info/METADATA
gorm_zhongwen_wendang_fix1-2025.3.25.1.dist-info/WHEEL
gorm_zhongwen_wendang_fix1-2025.3.25.1.dist-info/entry_points.txt
gorm_zhongwen_wendang_fix1-2025.3.25.1.dist-info/top_level.txt
gorm_zhongwen_wendang_fix1-2025.3.25.1.dist-info/RECORD
